{
  "videos": [
    {
      "id": "1",
      "title": "Underwater House - Digital Illustration [Procreate]",
      "upload_date": "2023-06-09 22:27:00",
      "uploader": "LinuxGamer",
      "description": "This is the first video",
      "video_file": "https://videos.danksquad.org/download/videos/925e9a4e-7e64-4b4b-a50e-81cbaec98edb-1088.mp4",
      "thumbnail_file": "thumbnails/thumbnail1.jpg"
    },
    {
      "id": "2",
      "title": "Video 2",
      "upload_date": "2023-06-14 14:45:00",
      "description": "This is the second video",
      "video_file": "videos/video2.mp4",
      "thumbnail_file": "thumbnails/thumbnail2.jpg"
    }
  ]
}
